{
  "fetched_at": "2026-03-22T08:46:59.921887",
  "regions": "us",
  "championship_probs": {
    "Michigan Wolverines": 0.19887510208104142,
    "Arizona Wildcats": 0.18252920327985991,
    "Duke Blue Devils": 0.1514162709026111,
    "Florida Gators": 0.09797523411345423,
    "Houston Cougars": 0.080268866502589,
    "Purdue Boilermakers": 0.048277651592136865,
    "Illinois Fighting Illini": 0.04626608277579783,
    "Iowa State Cyclones": 0.03331157959857444,
    "Michigan St Spartans": 0.026864177095624546,
    "UConn Huskies": 0.025822929921375533,
    "Arkansas Razorbacks": 0.020950678992814113,
    "St. John's Red Storm": 0.019144585976192206,
    "Virginia Cavaliers": 0.009410050734060576,
    "Nebraska Cornhuskers": 0.011688273543359452,
    "Tennessee Volunteers": 0.009683598720515826,
    "Kansas Jayhawks": 0.008144640488649007,
    "Alabama Crimson Tide": 0.005753295267456725,
    "UCLA Bruins": 0.0048701139763997715,
    "Texas Longhorns": 0.003684909247629916,
    "Texas Tech Red Raiders": 0.005054867920876243,
    "Kentucky Wildcats": 0.00401828463191489,
    "Miami Hurricanes": 0.0020767817704846906,
    "Iowa Hawkeyes": 0.002291030233739645,
    "Utah State Aggies": 0.0016217906328419884
  },
  "game_odds": [
    {
      "home_team": "Purdue Boilermakers",
      "away_team": "Miami Hurricanes",
      "commence_time": "2026-03-22T16:10:00Z",
      "home_prob": 0.7405693553336156,
      "away_prob": 0.2594306446663843
    },
    {
      "home_team": "Iowa State Cyclones",
      "away_team": "Kentucky Wildcats",
      "commence_time": "2026-03-22T18:45:00Z",
      "home_prob": 0.6678174034331731,
      "away_prob": 0.3321825965668268
    },
    {
      "home_team": "Wake Forest Demon Deacons",
      "away_team": "Illinois St Redbirds",
      "commence_time": "2026-03-22T20:30:00Z",
      "home_prob": 0.7301700574937053,
      "away_prob": 0.26982994250629466
    },
    {
      "home_team": "Kansas Jayhawks",
      "away_team": "St. John's Red Storm",
      "commence_time": "2026-03-22T21:15:00Z",
      "home_prob": 0.39391830320946547,
      "away_prob": 0.6060816967905345
    },
    {
      "home_team": "Virginia Cavaliers",
      "away_team": "Tennessee Volunteers",
      "commence_time": "2026-03-22T22:10:00Z",
      "home_prob": 0.4564714090894675,
      "away_prob": 0.5435285909105324
    },
    {
      "home_team": "Auburn Tigers",
      "away_team": "Seattle Redhawks",
      "commence_time": "2026-03-22T22:30:00Z",
      "home_prob": 0.8791804406557817,
      "away_prob": 0.12081955934421829
    },
    {
      "home_team": "Tulsa Golden Hurricane",
      "away_team": "UNLV Rebels",
      "commence_time": "2026-03-22T23:00:00Z",
      "home_prob": 0.632288565925407,
      "away_prob": 0.3677114340745929
    },
    {
      "home_team": "Florida Gators",
      "away_team": "Iowa Hawkeyes",
      "commence_time": "2026-03-22T23:10:00Z",
      "home_prob": 0.8244844624263742,
      "away_prob": 0.17551553757362576
    },
    {
      "home_team": "Arizona Wildcats",
      "away_team": "Utah State Aggies",
      "commence_time": "2026-03-22T23:50:00Z",
      "home_prob": 0.8530076175466246,
      "away_prob": 0.14699238245337537
    },
    {
      "home_team": "New Mexico Lobos",
      "away_team": "GW Revolutionaries",
      "commence_time": "2026-03-23T00:00:00Z",
      "home_prob": 0.7386058981233244,
      "away_prob": 0.2613941018766756
    },
    {
      "home_team": "Oklahoma St Cowboys",
      "away_team": "Wichita St Shockers",
      "commence_time": "2026-03-23T00:30:00Z",
      "home_prob": 0.5886640467584745,
      "away_prob": 0.41133595324152544
    },
    {
      "home_team": "UConn Huskies",
      "away_team": "UCLA Bruins",
      "commence_time": "2026-03-23T00:45:00Z",
      "home_prob": 0.6370311426194524,
      "away_prob": 0.3629688573805476
    },
    {
      "home_team": "California Golden Bears",
      "away_team": "Saint Joseph's Hawks",
      "commence_time": "2026-03-23T01:00:00Z",
      "home_prob": 0.6770926675114926,
      "away_prob": 0.3229073324885074
    },
    {
      "home_team": "Alabama Crimson Tide",
      "away_team": "Texas Tech Red Raiders",
      "commence_time": "2026-03-23T01:45:41Z",
      "home_prob": 0.45687529630384166,
      "away_prob": 0.5431247036961583
    },
    {
      "home_team": "Houston Cougars",
      "away_team": "Illinois Fighting Illini",
      "commence_time": "2026-03-26T16:00:00Z",
      "home_prob": 0.5760925725023092,
      "away_prob": 0.42390742749769084
    }
  ]
}